librid/__init__.py
librid/main.py
librid/core/__init__.py
librid/core/config.py
librid/core/document.py
librid/core/range.py
librid/core/sheet.py
librid/core/state.py
librid/utils/__init__.py
librid/utils/cleanup.py
librid/utils/connection.py
librid-0.0.2.dist-info/LICENSE.txt
librid-0.0.2.dist-info/METADATA
librid-0.0.2.dist-info/WHEEL
librid-0.0.2.dist-info/top_level.txt
librid-0.0.2.dist-info/RECORD
