Metadata-Version: 2.1
Name: librid
Version: 0.0.2
Summary: A simple python layer for ScriptForge
Home-page: https://gitlab.com/hemrichg/librid
Author: Stefan Hemrich
Author-email: hemrichg@pm.me
Project-URL: Bug Tracker, https://gitlab.com/hemrichg/librid/-/issues
Project-URL: repository, https://gitlab.com/hemrichg/librid
Classifier: Programming Language :: Python :: 3
Classifier: License :: OSI Approved :: MIT License
Classifier: Operating System :: OS Independent
Requires-Python: >=3.6
License-File: LICENSE.txt
